agents_integration/mcp_client/.env.example
agents_integration/mcp_client/.gitignore
agents_integration/mcp_client/.python-version
agents_integration/mcp_client/README.md
agents_integration/mcp_client/pyproject.toml
agents_integration/mcp_client/uv.lock
agents_integration/mcp_client/src/client.py
agents_integration/mcp_client/src/settings.py
agents_integration/mcp_client/src/utils/__init__.py
agents_integration/mcp_client/src/utils/command_utils.py
agents_integration/mcp_client/src/utils/handle_agent_loop_utils.py
agents_integration/mcp_client/src/utils/handle_message_utils.py
agents_integration/mcp_client/src/utils/llm_utils.py
agents_integration/mcp_client/src/utils/logging_utils.py
agents_integration/mcp_client/src/utils/opik_handler.py
agents_integration/mcp_client/src/utils/parse_message_utils.py
agents_integration/mcp_client/src/utils/print_utils.py
agents_integration/mcp_client/src/utils/types.py
agents_integration/mcp_server/pyproject.toml
agents_integration/mcp_server/uv.lock
agents_integration/mcp_server/src/__init__.py
agents_integration/mcp_server/src/main.py
research_agent_part_2/README.md
research_agent_part_2/data/research_function_calling/article_guideline.md
research_agent_part_2/data/sample_context_engineering/article_guideline.md
research_agent_part_2/data/sample_context_engineering/research.md
research_agent_part_2/data/sample_research_folder/article_guideline.md
research_agent_part_2/data/sample_research_folder/research.md
research_agent_part_2/data/sample_workflows_vs_agents/article_guideline.md
research_agent_part_2/mcp_client/.env.example
research_agent_part_2/mcp_client/.gitignore
research_agent_part_2/mcp_client/.python-version
research_agent_part_2/mcp_client/README.md
research_agent_part_2/mcp_client/pyproject.toml
research_agent_part_2/mcp_client/uv.lock
research_agent_part_2/mcp_client/src/client.py
research_agent_part_2/mcp_client/src/settings.py
research_agent_part_2/mcp_client/src/utils/__init__.py
agentic_ai_engineering_course-0.4.6.dist-info/METADATA
agentic_ai_engineering_course-0.4.6.dist-info/WHEEL
agentic_ai_engineering_course-0.4.6.dist-info/licenses/LICENSE
agentic_ai_engineering_course-0.4.6.dist-info/RECORD
