Metadata-Version: 2.4
Name: agentic-ai-engineering-course
Version: 0.4.6
Summary: Python modules for the Agentic AI Engineering course by Towards AI and Decoding ML.
Project-URL: Homepage, https://github.com/towardsai/agentic-ai-engineering-course
Project-URL: Repository, https://github.com/towardsai/agentic-ai-engineering-course
Project-URL: Issues, https://github.com/towardsai/agentic-ai-engineering-course/issues
Author-email: Paul Iusztin <p.b.iusztin@gmail.com>, Fabio chiusano <chiusanofabio94@gmail.com>, Omar solano <omarsolano27@gmail.com>
License: Apache-2.0
License-File: LICENSE
Keywords: agents,ai,workflows
Classifier: Development Status :: 3 - Alpha
Classifier: Intended Audience :: Developers
Classifier: License :: OSI Approved :: Apache Software License
Classifier: Programming Language :: Python :: 3
Classifier: Programming Language :: Python :: 3.12
Requires-Python: >=3.12.11
Requires-Dist: aiosqlite>=0.21.0
Requires-Dist: chromadb>=1.0.20
Requires-Dist: click>=8.1.8
Requires-Dist: fastmcp==2.12.0
Requires-Dist: firecrawl-py>=2.7.1
Requires-Dist: gitingest>=0.1.5
Requires-Dist: google-genai>=1.24.0
Requires-Dist: ipywidgets>=8.1.8
Requires-Dist: langchain-community>=0.4.1
Requires-Dist: langchain-google-genai>=3.0.0
Requires-Dist: langchain-perplexity>=0.1.2
Requires-Dist: langchain>=1.0.3
Requires-Dist: langgraph-checkpoint-sqlite>=3.0.0
Requires-Dist: langgraph>=1.0.3
Requires-Dist: loguru>=0.7.3
Requires-Dist: matplotlib>=3.10.3
Requires-Dist: mem0ai>=0.1.116
Requires-Dist: opik>=1.7.42
Requires-Dist: pillow>=11.3.0
Requires-Dist: pydantic-settings>=2.9.1
Requires-Dist: pydantic>=2.11.7
Requires-Dist: python-dotenv>=1.1.0
Requires-Dist: pyyaml>=6.0.1
Requires-Dist: requests>=2.32.4
Requires-Dist: scikit-learn>=1.7.0
